downdetecthon/DDAuth.py
downdetecthon/__init__.py
downdetecthon-0.0.1.dist-info/METADATA
downdetecthon-0.0.1.dist-info/WHEEL
downdetecthon-0.0.1.dist-info/top_level.txt
downdetecthon-0.0.1.dist-info/RECORD
