Metadata-Version: 2.1
Name: downdetecthon
Version: 0.0.1
Summary: Down Detector APIs utils
Home-page: UNKNOWN
Author: SteveEmmE (Stefano Monti)
Author-email: <stefano.monti02@gmail.com>
License: UNKNOWN
Keywords: python,api,rest,requests,down detector,web service
Platform: UNKNOWN
Classifier: Development Status :: 1 - Planning
Classifier: Intended Audience :: Developers
Classifier: Programming Language :: Python :: 3
Classifier: Operating System :: Unix
Classifier: Operating System :: MacOS :: MacOS X
Classifier: Operating System :: Microsoft :: Windows
Requires-Dist: requests
